higgsboom/DataBaseUtils.py
higgsboom/DataUtils.py
higgsboom/DatabaseManager.py
higgsboom/Exceptions.py
higgsboom/FactorsGeneratorBase.py
higgsboom/FactorsLibManager.py
higgsboom/MarketDataUtils.py
higgsboom/TrainingUtils.py
higgsboom/__init__.py
higgsboom/TrainingUtils/MultiInstrumentTickTrainingUtils.py
higgsboom/TrainingUtils/TrainingUtils.py
higgsboom/TrainingUtils/__init__.py
higgsboom-old/DatabaseManager.py
higgsboom-old/Exceptions.py
higgsboom-old/FactorsGeneratorBase.py
higgsboom-old/MarketDataUtils.py
higgsboom-old/TrainingUtils.py
higgsboom-old/__init__.py
higgsboom-0.1.5.dist-info/LICENSE.txt
higgsboom-0.1.5.dist-info/METADATA
higgsboom-0.1.5.dist-info/WHEEL
higgsboom-0.1.5.dist-info/top_level.txt
higgsboom-0.1.5.dist-info/RECORD
