Metadata-Version: 2.1
Name: higgsboom
Version: 0.1.5
Summary: Higgs Asset Management Boom Strategy Platform API
Home-page: https://github.com/veidt1988/higgs-boom-master
Author: Veidt
Author-email: veidt1988@live.com
License: UNKNOWN
Platform: UNKNOWN
Classifier: Development Status :: 3 - Alpha
Classifier: Topic :: Software Development :: Build Tools
Classifier: License :: OSI Approved :: MIT License
Requires-Python: >=3.5
Requires-Dist: sqlalchemy
Requires-Dist: mysqlclient
Requires-Dist: numpy
Requires-Dist: pandas
